{
  "property" : {
    "type" : "Energy",
    "wfn" : "$:mp2"
  },
  "mp2":{
    "type": "MP2",
    "frozen_core" : true,
    "atoms" : "$:water",
    "wfn_world" : "$:wfn_world",
    "ref" : "$:rhf"
  },
  "wfn_world":{
    "type" : "WfnWorld",
    "atoms" : "$:water",
    "basis" : "$:basis"
  },
  "rhf":{
    "type": "RHF",
    "atoms" : "$:water",
    "wfn_world" : "$:wfn_world",
    "localize" : true
  },
  "water": {
    "atoms": [
      { "element": "O", "xyz":[ 0.00000, -0.07579,  0.00000] },
      { "element": "H", "xyz":[ 0.86681,  0.60144,  0.00000] },
      { "element": "H", "xyz":[-0.86681,  0.60144,  0.00000] }
    ]
  },
  "basis": {
    "name": "6-31G",
    "atoms": "$:water"
  }
}

